{"China": 1411778724,
"India": 1378412004,
"United States": 331876560,
"Indonesia": 271350000,
"Pakistan": 225200000,
"Brazil": 213296085,
"Nigeria": 211401000,
"Bangladesh": 170869864,
"Russia": 146171015,
"Mexico": 126014024,
"Japan": 125360000,
"Ethiopia": 117876000,
"Philippines": 110381624,
"Egypt": 101942945,
"Vietnam": 97580000,
"Democratic Republic of Congo": 92378000,
"Iran": 84542384,
"Turkey": 83614362,
"Germany": 83190556,
"France": 67413000,
"United Kingdom": 67113000,
"Thailand": 66660655,
"South Africa": 59622350,
"Tanzania": 59441988,
"Italy": 59204919,
"Myanmar": 55294979,
"South Korea": 51683025,
"Colombia": 51049498,
"Kenya": 47564296,
"Spain": 47351567,
"Argentina": 45808747,
"Algeria": 44700000,
"Sudan": 43563080,
"Uganda": 42885900,
"Ukraine": 41442615,
"Iraq": 41190700,
"Canada": 38304826,
"Poland": 38208000,
"Morocco": 36284852,
"Uzbekistan": 34929179,
"Saudi Arabia": 34218169,
"Peru": 33035304,
"Afghanistan": 32890171,
"Malaysia": 32778350,
"Angola": 32097671,
"Ghana": 30955202,
"Mozambique": 30832244,
"Yemen": 30491000,
"Nepal": 30378055,
"Venezuela": 28705000,
"Ivory Coast": 27087732,
"Madagascar": 26923353,
"Australia": 25817188,
"North Korea": 25660000,
"Cameroon": 24348251,
"Niger": 24112753,
"Taiwan": 23514196,
"Sri Lanka": 21919000,
"Burkina Faso": 21510181,
"Mali": 20856000,
"Chile": 19678363,
"Romania": 19317984,
"Kazakhstan": 18947976,
"Malawi": 18898441,
"Zambia": 18400556,
"Syria": 18276000,
"Ecuador": 17756868,
"Netherlands": 17606431,
"Senegal": 17223497,
"Guatemala": 17109746,
"Chad": 16818391,
"Somalia": 16360000,
"Zimbabwe": 15790716,
"Cambodia": 15552211,
"South Sudan": 13249924,
"Rwanda": 12955768,
"Guinea": 12907395,
"Burundi": 12574571,
"Benin": 12506347,
"Bolivia": 11797257,
"Tunisia": 11746695,
"Haiti": 11743017,
"Belgium": 11565582,
"Cuba": 11181595,
"Jordan": 10970852,
"Greece": 10718565,
"Czech Republic": 10694480,
"Dominican Republic": 10535535,
"Sweden": 10395160,
"Portugal": 10298252,
"Azerbaijan": 10130100,
"Hungary": 9730000,
"Tajikistan": 9504000,
"United Arab Emirates": 9503738,
"Honduras": 9450711,
"Israel": 9360973,
"Belarus": 9349645,
"Papua New Guinea": 9122994,
"Austria": 8940809,
"Switzerland": 8667100,
"Sierra Leone": 8297882,
"Togo": 7886000,
"Hong Kong": 7474200,
"Paraguay": 7353038,
"Laos": 7337783,
"Libya": 6959000,
"Serbia": 6926705,
"Bulgaria": 6916548,
"El Salvador": 6825935,
"Lebanon": 6769000,
"Kyrgyz Republic": 6663000,
"Nicaragua": 6595674,
"Turkmenistan": 6118000,
"Denmark": 5843347,
"Singapore": 5685807,
"Congo": 5657000,
"Central African Republic": 5633412,
"Finland": 5508187,
"Slovak Republic": 5459781,
"Norway": 5398804,
"Palestine": 5227193,
"Costa Rica": 5163038,
"New Zealand": 5123668,
"Ireland": 4977400,
"Liberia": 4661010,
"Oman": 4513666,
"Kuwait": 4464521,
"Panama": 4278500,
"Mauritania": 4271197,
"Croatia": 4047200,
"Georgia": 3728573,
"Eritrea": 3601000,
"Uruguay": 3554915,
"Mongolia": 3383362,
"Bosnia and Herzegovina": 3320954,
"Puerto Rico": 3285874,
"Armenia": 2963300,
"Albania": 2829741,
"Lithuania": 2786006,
"Jamaica": 2734093,
"Moldova": 2640438,
"Qatar": 2628512,
"Namibia": 2550226,
"Gambia": 2487000,
"Botswana": 2410338,
"Gabon": 2233272,
"Lesotho": 2159000,
"Slovenia": 2108977,
"North Macedonia": 2076255,
"Latvia": 1885400,
"Kosovo": 1782115,
"Guinea-Bissau": 1646077,
"Equatorial Guinea": 1505588,
"Bahrain": 1501635,
"Trinidad and Tobago": 1366725,
"Estonia": 1330068,
"Timor-Leste": 1317780,
"Mauritius": 1266030,
"Eswatini": 1172000,
"Djibouti": 976107,
"Fiji": 898402,
"Cyprus": 888005,
"Comoros": 758316,
"Bhutan": 756129,
"Guyana": 743699,
"Solomon Islands": 728041,
"Macau": 682500,
"Luxembourg": 634730,
"Montenegro": 621306,
"Western Sahara": 612000,
"Suriname": 598000,
"Cape Verde": 563198,
"Malta": 514564,
"Transnistria": 469000,
"Brunei": 453600,
"Belize": 419199,
"Bahamas": 393450,
"Maldives": 383135,
"Northern Cyprus": 372486,
"Iceland": 369870,
"Vanuatu": 301295,
"Barbados": 288000,
"French Polynesia": 279890,
"New Caledonia": 273674,
"Abkhazia": 245424,
"São Tomé and Príncipe": 214610,
"Samoa": 199853,
"Saint Lucia": 178696,
"Guam": 178306,
"Curaçao": 153671,
"Republic of Artsakh": 148900,
"Kiribati": 120740,
"Grenada": 113000,
"Aruba": 111050,
"Saint Vincent and the Grenadines": 110696,
"Jersey": 107800,
"Micronesia": 105754,
"United States Virgin Islands": 104000,
"Tonga": 99532,
"Antigua and Barbuda": 99337,
"Seychelles": 98963,
"Isle of Man": 85000,
"Andorra": 78015,
"Dominica": 72000,
"Cayman Islands": 65786,
"Bermuda": 64055,
"Guernsey": 63124,
"American Samoa": 56951,
"Northern Mariana Islands": 56801,
"Greenland": 56541,
"Marshall Islands": 54516,
"Saint Kitts and Nevis": 54000,
"South Ossetia": 53532,
"Faroe Islands": 53305,
"Turks and Caicos Islands": 42953,
"Sint Maarten": 41486,
"Liechtenstein": 39062,
"Monaco": 38350,
"Saint Martin": 34065,
"Gibraltar": 34000,
"San Marino": 33593,
"Åland Islands": 30237,
"British Virgin Islands": 30000,
"Palau": 17957,
"Cook Islands": 15342,
"Anguilla": 15000,
"Nauru": 11832,
"Wallis and Futuna": 11369,
"Tuvalu": 10679,
"Saint Barthélemy": 10124,
"Saint Helena Ascension and Tristan da Cunha": 6000,
"Saint Pierre and Miquelon": 5985,
"Montserrat": 5000,
"Falkland Islands": 4000,
"Christmas Island": 1966,
"Norfolk Island": 1734,
"Niue": 1549,
"Tokelau": 1501,
"Vatican City": 825,
"Cocos (Keeling) Islands": 573,
"Pitcairn Islands": 40
}